{"client":"Thunder Client","collectionName":"Final Project","dateExported":"2021-10-06T13:52:25.045Z","version":"1.1","folders":[],"requests":[{"containerId":"","sortNum":20000,"headers":[{"name":"Accept","value":"*/*"},{"name":"User-Agent","value":"Thunder Client (https://www.thunderclient.io)"}],"colId":"28eb6afd-f888-4333-bfbf-84729086f3c8","name":"AddUser","url":"127.0.0.1:8081/user","method":"POST","modified":"2021-10-06T09:33:07.328Z","created":"2021-10-06T09:24:51.099Z","_id":"2d8cb52a-ad02-4146-8d63-d30f8ad26a0e","params":[],"body":{"type":"json","raw":"{\"Name\":\"Radesh\"}","form":[]},"tests":[]},{"containerId":"","sortNum":30000,"headers":[{"name":"Accept","value":"*/*"},{"name":"User-Agent","value":"Thunder Client (https://www.thunderclient.io)"}],"colId":"28eb6afd-f888-4333-bfbf-84729086f3c8","name":"UpdateUser","url":"127.0.0.1:8081/user","method":"PUT","modified":"2021-10-06T11:11:17.083Z","created":"2021-10-06T09:33:37.032Z","_id":"cf2d4502-04c1-4797-b5a7-131bcb12817b","params":[],"body":{"type":"json","raw":"{ \"userID\": 4, \"Name\":\"Radesh\"}","form":[]},"tests":[]},{"containerId":"","sortNum":40000,"headers":[{"name":"Accept","value":"*/*"},{"name":"User-Agent","value":"Thunder Client (https://www.thunderclient.io)"}],"colId":"28eb6afd-f888-4333-bfbf-84729086f3c8","name":"DeleteUser","url":"127.0.0.1:8081/user?id=8","method":"DELETE","modified":"2021-10-06T12:30:16.809Z","created":"2021-10-06T09:40:50.817Z","_id":"c5e65487-de1d-4fc6-90d4-2b6a5b27aad4","params":[{"name":"id","value":"8","isPath":false}],"tests":[]},{"containerId":"","sortNum":50000,"headers":[{"name":"Accept","value":"*/*"},{"name":"User-Agent","value":"Thunder Client (https://www.thunderclient.io)"}],"colId":"28eb6afd-f888-4333-bfbf-84729086f3c8","name":"GetTodos","url":"127.0.0.1:8081/api/todos","method":"GET","modified":"2021-10-06T09:53:30.525Z","created":"2021-10-06T09:53:00.534Z","_id":"ee6eeb6b-aaae-4004-abe7-8464f22467da","params":[],"body":{"type":"json","raw":"{\"Name\":\"Radesh\"}","form":[]},"tests":[]},{"containerId":"","sortNum":60000,"headers":[{"name":"Accept","value":"*/*"},{"name":"User-Agent","value":"Thunder Client (https://www.thunderclient.io)"}],"colId":"28eb6afd-f888-4333-bfbf-84729086f3c8","name":"GetTodo","url":"127.0.0.1:8081/api/todo?id=1","method":"GET","modified":"2021-10-06T09:55:20.311Z","created":"2021-10-06T09:55:03.677Z","_id":"c59b2981-eef1-4def-8f11-57b5a1c03e6d","params":[{"name":"id","value":"1","isPath":false}],"body":{"type":"json","raw":"{\"Name\":\"Radesh\"}","form":[]},"tests":[]},{"containerId":"","sortNum":70000,"headers":[{"name":"Accept","value":"*/*"},{"name":"User-Agent","value":"Thunder Client (https://www.thunderclient.io)"}],"colId":"28eb6afd-f888-4333-bfbf-84729086f3c8","name":"AddTodo","url":"127.0.0.1:8081/api/todo","method":"POST","modified":"2021-10-06T10:13:33.807Z","created":"2021-10-06T10:01:15.509Z","_id":"dd574f45-882a-40cb-acd8-63762db8304c","params":[],"body":{"type":"json","raw":"{\"Title\":\"Some Title\",\"Desc\":\"Some Desc\",\"DueDate\":\"2021-10-10\",\"PersonInCharge\":1,\"Status\":1}","form":[]},"tests":[]},{"containerId":"","sortNum":80000,"headers":[{"name":"Accept","value":"*/*"},{"name":"User-Agent","value":"Thunder Client (https://www.thunderclient.io)"}],"colId":"28eb6afd-f888-4333-bfbf-84729086f3c8","name":"UpdateTodo","url":"127.0.0.1:8081/api/todo","method":"PUT","modified":"2021-10-06T10:18:22.561Z","created":"2021-10-06T10:14:50.626Z","_id":"06f381d0-3790-4258-a340-e3408fd61173","params":[],"body":{"type":"json","raw":"{\"ID\":2, \"Title\":\"Upate Title\",\"Desc\":\"Some Desc Upate\",\"DueDate\":\"2021-10-09\",\"PersonInCharge\":2,\"Status\":2}","form":[]},"tests":[]},{"containerId":"","sortNum":90000,"headers":[{"name":"Accept","value":"*/*"},{"name":"User-Agent","value":"Thunder Client (https://www.thunderclient.io)"}],"colId":"28eb6afd-f888-4333-bfbf-84729086f3c8","name":"DeleteTodo","url":"127.0.0.1:8081/api/todo?id=2","method":"DELETE","modified":"2021-10-06T10:21:52.054Z","created":"2021-10-06T10:19:30.091Z","_id":"8592c2e9-f175-4181-8405-18d10b13d52a","params":[{"name":"id","value":"2","isPath":false}],"tests":[]}]}
